qcs_api_client/__init__.py
qcs_api_client/api/__init__.py
qcs_api_client/api/account/__init__.py
qcs_api_client/api/account/activate_user.py
qcs_api_client/api/account/add_group_user.py
qcs_api_client/api/account/dismiss_viewer_announcement.py
qcs_api_client/api/account/get_group_balance.py
qcs_api_client/api/account/get_group_billing_customer.py
qcs_api_client/api/account/get_group_upcoming_billing_invoice.py
qcs_api_client/api/account/get_user_balance.py
qcs_api_client/api/account/get_user_billing_customer.py
qcs_api_client/api/account/get_user_event_billing_price.py
qcs_api_client/api/account/get_user_upcoming_billing_invoice.py
qcs_api_client/api/account/get_viewer_user_onboarding_completed.py
qcs_api_client/api/account/list_group_billing_invoice_lines.py
qcs_api_client/api/account/list_group_billing_invoices.py
qcs_api_client/api/account/list_group_upcoming_billing_invoice_lines.py
qcs_api_client/api/account/list_group_users.py
qcs_api_client/api/account/list_user_billing_invoice_lines.py
qcs_api_client/api/account/list_user_billing_invoices.py
qcs_api_client/api/account/list_user_groups.py
qcs_api_client/api/account/list_user_upcoming_billing_invoice_lines.py
qcs_api_client/api/account/list_viewer_announcements.py
qcs_api_client/api/account/put_viewer_user_onboarding_completed.py
qcs_api_client/api/account/remove_group_user.py
qcs_api_client/api/account/update_viewer_user_profile.py
qcs_api_client/api/authentication/__init__.py
qcs_api_client/api/authentication/auth_email_password_reset_token.py
qcs_api_client/api/authentication/auth_get_user.py
qcs_api_client/api/authentication/auth_reset_password.py
qcs_api_client/api/authentication/auth_reset_password_with_token.py
qcs_api_client/api/client_applications/__init__.py
qcs_api_client/api/client_applications/check_client_application.py
qcs_api_client/api/client_applications/get_client_application.py
qcs_api_client/api/client_applications/list_client_applications.py
qcs_api_client/api/default/__init__.py
qcs_api_client-0.26.5.dist-info/LICENSE
qcs_api_client-0.26.5.dist-info/METADATA
qcs_api_client-0.26.5.dist-info/WHEEL
qcs_api_client-0.26.5.dist-info/RECORD
