Metadata-Version: 2.3
Name: qcs-api-client
Version: 0.26.5
Summary: A client library for accessing the Rigetti QCS API
License: Apache-2.0
Requires-Python: >=3.8,<4.0
Classifier: License :: OSI Approved :: Apache Software License
Classifier: Programming Language :: Python :: 3
Classifier: Programming Language :: Python :: 3.8
Classifier: Programming Language :: Python :: 3.9
Classifier: Programming Language :: Python :: 3.10
Classifier: Programming Language :: Python :: 3.11
Classifier: Programming Language :: Python :: 3.12
Classifier: Programming Language :: Python :: 3.13
Requires-Dist: PyJWT (>=2.4.0,<3.0.0)
Requires-Dist: attrs (>=21.3.0)
Requires-Dist: httpx (>=0.23.0,<1.0)
Requires-Dist: iso8601 (>=1.0.2,<2.0.0)
Requires-Dist: pydantic (>=2.6.3,<3.0.0)
Requires-Dist: pydantic-settings (>=2.2.1,<2.9)
Requires-Dist: python-dateutil (>=2.8.1,<3.0.0)
Requires-Dist: rfc3339 (>=6.2,<7.0)
Requires-Dist: tenacity (>=8.3.0,<9.0.0)
Requires-Dist: toml (>=0.10.2,<0.11.0)
Project-URL: Documentation, https://qcs-api-client-python.readthedocs.io/en/latest/index.html
Project-URL: Repository, https://github.com/rigetti/qcs-api-client-python
